[{"article_id": 19224945, "funder": null}, {"article_id": 19224936, "funder": null}, {"article_id": 19224924, "funder": null}, {"article_id": 19224915, "funder": null}, {"article_id": 19224912, "funder": null}, {"article_id": 19224909, "funder": null}, {"article_id": 19224903, "funder": null}, {"article_id": 19224897, "funder": null}, {"article_id": 19224894, "funder": null}, {"article_id": 19224870, "funder": null}, {"article_id": 16934038, "funder": "Directorate for Geosciences"}, {"article_id": 14264195, "funder": "Directorate for Biological Sciences"}, {"article_id": 14264195, "funder": null}, {"article_id": 14264195, "funder": null}, {"article_id": 14264195, "funder": null}, {"article_id": 19111376, "funder": null}, {"article_id": 19111376, "funder": null}, {"article_id": 19111376, "funder": null}, {"article_id": 18190784, "funder": null}, {"article_id": 18190784, "funder": null}, {"article_id": 17152811, "funder": null}, {"article_id": 17152811, "funder": null}, {"article_id": 17152811, "funder": null}, {"article_id": 16725439, "funder": "Directorate for Biological Sciences"}, {"article_id": 16725439, "funder": "Directorate for Biological Sciences"}, {"article_id": 16725439, "funder": "Directorate for Biological Sciences"}, {"article_id": 7070216, "funder": null}, {"article_id": 7070216, "funder": null}, {"article_id": 7070216, "funder": null}, {"article_id": 7828334, "funder": null}, {"article_id": 7828334, "funder": null}, {"article_id": 7828334, "funder": null}, {"article_id": 6459086, "funder": null}, {"article_id": 6459086, "funder": null}, {"article_id": 12644940, "funder": null}, {"article_id": 12644940, "funder": "Directorate for Engineering"}, {"article_id": 12645774, "funder": null}, {"article_id": 12645774, "funder": "Directorate for Engineering"}, {"article_id": 17213138, "funder": "United States Department of Agriculture"}, {"article_id": 17213138, "funder": null}, {"article_id": 17213138, "funder": "National Institute of Food and Agriculture"}, {"article_id": 17213138, "funder": "National Institute of Food and Agriculture"}, {"article_id": 16862209, "funder": "National Institute of Justice"}, {"article_id": 15070029, "funder": "Directorate for Biological Sciences"}, {"article_id": 15070029, "funder": "Directorate for Biological Sciences"}, {"article_id": 14885825, "funder": null}, {"article_id": 14885825, "funder": "Directorate for Engineering"}, {"article_id": 14887854, "funder": null}, {"article_id": 14887854, "funder": "Directorate for Engineering"}, {"article_id": 12645919, "funder": null}, {"article_id": 12645919, "funder": "Directorate for Engineering"}, {"article_id": 12646255, "funder": null}, {"article_id": 12646255, "funder": "Directorate for Engineering"}, {"article_id": 12645805, "funder": null}, {"article_id": 12645805, "funder": "Directorate for Engineering"}, {"article_id": 12645692, "funder": null}, {"article_id": 12645692, "funder": "Directorate for Engineering"}, {"article_id": 12645741, "funder": null}, {"article_id": 12645741, "funder": "Directorate for Engineering"}, {"article_id": 12645482, "funder": null}, {"article_id": 12645482, "funder": "Directorate for Engineering"}, {"article_id": 12645528, "funder": null}, {"article_id": 12645528, "funder": "Directorate for Engineering"}, {"article_id": 12645569, "funder": null}, {"article_id": 12645569, "funder": "Directorate for Engineering"}, {"article_id": 12645600, "funder": null}, {"article_id": 12645600, "funder": "Directorate for Engineering"}, {"article_id": 12645365, "funder": null}, {"article_id": 12645365, "funder": "Directorate for Engineering"}, {"article_id": 12645380, "funder": null}, {"article_id": 12645380, "funder": "Directorate for Engineering"}, {"article_id": 12645399, "funder": null}, {"article_id": 12645399, "funder": "Directorate for Engineering"}, {"article_id": 12645452, "funder": null}, {"article_id": 12645452, "funder": "Directorate for Engineering"}, {"article_id": 12645291, "funder": null}, {"article_id": 12645291, "funder": "Directorate for Engineering"}, {"article_id": 12645318, "funder": null}, {"article_id": 12645318, "funder": "Directorate for Engineering"}, {"article_id": 12645336, "funder": null}, {"article_id": 12645336, "funder": "Directorate for Engineering"}, {"article_id": 12645344, "funder": null}, {"article_id": 12645344, "funder": "Directorate for Engineering"}, {"article_id": 12645217, "funder": null}, {"article_id": 12645217, "funder": "Directorate for Engineering"}, {"article_id": 12645234, "funder": null}, {"article_id": 12645234, "funder": "Directorate for Engineering"}, {"article_id": 12645006, "funder": null}, {"article_id": 12645006, "funder": "Directorate for Engineering"}, {"article_id": 12645045, "funder": null}, {"article_id": 12645045, "funder": "Directorate for Engineering"}, {"article_id": 12644917, "funder": null}, {"article_id": 12644917, "funder": "Directorate for Engineering"}, {"article_id": 12644947, "funder": null}, {"article_id": 12644947, "funder": "Directorate for Engineering"}, {"article_id": 12644890, "funder": null}, {"article_id": 12644890, "funder": "Directorate for Engineering"}, {"article_id": 12644847, "funder": null}, {"article_id": 12644847, "funder": "Directorate for Engineering"}, {"article_id": 12644859, "funder": null}, {"article_id": 12644859, "funder": "Directorate for Engineering"}, {"article_id": 12644887, "funder": null}, {"article_id": 12644887, "funder": "Directorate for Engineering"}, {"article_id": 12644830, "funder": null}, {"article_id": 12644830, "funder": "Directorate for Engineering"}, {"article_id": 12644233, "funder": null}, {"article_id": 12644233, "funder": "Directorate for Engineering"}, {"article_id": 12644247, "funder": null}, {"article_id": 12644247, "funder": "Directorate for Engineering"}, {"article_id": 12644812, "funder": null}, {"article_id": 12644812, "funder": "Directorate for Engineering"}, {"article_id": 12644226, "funder": null}, {"article_id": 12644226, "funder": "Directorate for Engineering"}, {"article_id": 14832252, "funder": null}, {"article_id": 14762355, "funder": null}, {"article_id": 14762355, "funder": null}, {"article_id": 15082791, "funder": null}, {"article_id": 15046578, "funder": null}, {"article_id": 15046578, "funder": null}, {"article_id": 15046578, "funder": null}, {"article_id": 14695989, "funder": "Biological and Environmental Research"}, {"article_id": 14695989, "funder": "National Institute of Food and Agriculture"}, {"article_id": 14036000, "funder": null}, {"article_id": 14394455, "funder": null}, {"article_id": 14439494, "funder": "United States Department of the Navy"}, {"article_id": 14394443, "funder": null}, {"article_id": 13626731, "funder": null}, {"article_id": 13708300, "funder": "Directorate for Biological Sciences"}, {"article_id": 12245846, "funder": "Directorate for Biological Sciences"}, {"article_id": 13713589, "funder": null}, {"article_id": 13656314, "funder": "National Institute of Food and Agriculture"}, {"article_id": 13656314, "funder": "National Institute of Food and Agriculture"}, {"article_id": 13661705, "funder": "National Institute of Food and Agriculture"}, {"article_id": 13661705, "funder": "National Institute of Food and Agriculture"}, {"article_id": 13175180, "funder": null}, {"article_id": 13222085, "funder": "Directorate for Biological Sciences"}, {"article_id": 12762011, "funder": "Directorate for Education & Human Resources"}, {"article_id": 12762011, "funder": "National Institute of Food and Agriculture"}, {"article_id": 12762011, "funder": null}, {"article_id": 13043486, "funder": "National Institute of Food and Agriculture"}, {"article_id": 12287951, "funder": null}, {"article_id": 12287951, "funder": null}, {"article_id": 8018600, "funder": null}, {"article_id": 8018600, "funder": null}, {"article_id": 8181866, "funder": null}, {"article_id": 8181866, "funder": null}, {"article_id": 12779954, "funder": null}, {"article_id": 12779954, "funder": "Directorate for Geosciences"}, {"article_id": 12779954, "funder": "Directorate for Geosciences"}, {"article_id": 12779954, "funder": "National Aeronautics and Space Administration"}, {"article_id": 12779954, "funder": "National Oceanic and Atmospheric Administration"}, {"article_id": 12385709, "funder": "Directorate for Geosciences"}, {"article_id": 12685775, "funder": null}, {"article_id": 12668843, "funder": "Directorate for Engineering"}, {"article_id": 12668843, "funder": "Directorate for Mathematical & Physical Sciences"}, {"article_id": 12668843, "funder": "United States Department of the Navy"}, {"article_id": 12668843, "funder": null}, {"article_id": 12668843, "funder": null}, {"article_id": 12668843, "funder": null}, {"article_id": 12668843, "funder": null}, {"article_id": 12668843, "funder": null}, {"article_id": 12605624, "funder": null}, {"article_id": 12563924, "funder": "Directorate for Mathematical & Physical Sciences"}, {"article_id": 12563924, "funder": "United States Department of the Army"}, {"article_id": 12563924, "funder": null}, {"article_id": 12563924, "funder": "United States Department of the Navy"}, {"article_id": 12563924, "funder": "Directorate for Engineering"}, {"article_id": 11624073, "funder": null}, {"article_id": 12582110, "funder": null}, {"article_id": 12550790, "funder": null}, {"article_id": 12550790, "funder": null}, {"article_id": 12550790, "funder": null}, {"article_id": 12550790, "funder": null}, {"article_id": 12298955, "funder": "Directorate for Biological Sciences"}, {"article_id": 12298955, "funder": "Directorate for Biological Sciences"}, {"article_id": 12145752, "funder": "Directorate for Biological Sciences"}, {"article_id": 12145752, "funder": null}, {"article_id": 12145752, "funder": "National Institute of General Medical Sciences"}, {"article_id": 12209984, "funder": null}, {"article_id": 12209984, "funder": null}, {"article_id": 12206720, "funder": null}, {"article_id": 12206720, "funder": null}, {"article_id": 12206705, "funder": null}, {"article_id": 12206705, "funder": null}, {"article_id": 12290585, "funder": "Directorate for Biological Sciences"}, {"article_id": 12290585, "funder": "National Institute on Aging"}, {"article_id": 11916081, "funder": null}, {"article_id": 11916081, "funder": null}, {"article_id": 8178938, "funder": "Directorate for Biological Sciences"}, {"article_id": 12146172, "funder": null}, {"article_id": 12030744, "funder": "Directorate for Geosciences"}, {"article_id": 12030744, "funder": "Directorate for Geosciences"}, {"article_id": 12030744, "funder": null}, {"article_id": 12030744, "funder": null}, {"article_id": 12030744, "funder": null}, {"article_id": 12030744, "funder": null}, {"article_id": 11933214, "funder": "Directorate for Education & Human Resources"}, {"article_id": 8016341, "funder": null}, {"article_id": 8016341, "funder": null}, {"article_id": 11371506, "funder": "Office of the Director"}, {"article_id": 11371506, "funder": "Directorate for Education & Human Resources"}, {"article_id": 11371506, "funder": "Directorate for Geosciences"}, {"article_id": 11371506, "funder": null}, {"article_id": 11371506, "funder": null}, {"article_id": 8020583, "funder": null}, {"article_id": 8020583, "funder": null}, {"article_id": 9827243, "funder": null}, {"article_id": 9827243, "funder": null}, {"article_id": 8018588, "funder": null}, {"article_id": 8018588, "funder": null}, {"article_id": 9879716, "funder": null}, {"article_id": 9879716, "funder": null}, {"article_id": 11366153, "funder": null}, {"article_id": 11366153, "funder": null}, {"article_id": 11366003, "funder": null}, {"article_id": 11366003, "funder": null}, {"article_id": 11366192, "funder": null}, {"article_id": 11366192, "funder": null}, {"article_id": 11503833, "funder": null}, {"article_id": 11354111, "funder": "Directorate for Geosciences"}, {"article_id": 11354111, "funder": null}, {"article_id": 10275884, "funder": null}, {"article_id": 10779986, "funder": null}, {"article_id": 10779986, "funder": null}, {"article_id": 11356430, "funder": null}, {"article_id": 11343020, "funder": "National Institute of General Medical Sciences"}, {"article_id": 11343020, "funder": "Directorate for Biological Sciences"}, {"article_id": 11343020, "funder": "National Institute of Allergy and Infectious Diseases"}, {"article_id": 8018612, "funder": null}, {"article_id": 8018612, "funder": null}, {"article_id": 10022984, "funder": "Directorate for Geosciences"}, {"article_id": 8018606, "funder": null}, {"article_id": 8018606, "funder": null}, {"article_id": 10062203, "funder": null}, {"article_id": 8214428, "funder": null}, {"article_id": 7771010, "funder": null}, {"article_id": 7800956, "funder": null}, {"article_id": 8023580, "funder": "Directorate for Biological Sciences"}, {"article_id": 7635962, "funder": null}, {"article_id": 7635962, "funder": "Directorate for Biological Sciences"}, {"article_id": 7635962, "funder": "Directorate for Engineering"}, {"article_id": 7635962, "funder": null}, {"article_id": 7635959, "funder": null}, {"article_id": 7635959, "funder": "Directorate for Biological Sciences"}, {"article_id": 7635959, "funder": "Directorate for Engineering"}, {"article_id": 7635959, "funder": null}, {"article_id": 7746635, "funder": "Directorate for Geosciences"}, {"article_id": 7455404, "funder": null}, {"article_id": 6333104, "funder": null}, {"article_id": 7528772, "funder": null}, {"article_id": 7528772, "funder": null}, {"article_id": 7528772, "funder": null}, {"article_id": 7218857, "funder": null}, {"article_id": 7218857, "funder": "Directorate for Biological Sciences"}, {"article_id": 7218857, "funder": "Directorate for Computer & Information Science & Engineering"}, {"article_id": 7218866, "funder": null}, {"article_id": 7218866, "funder": "Directorate for Biological Sciences"}, {"article_id": 7218866, "funder": "Directorate for Computer & Information Science & Engineering"}, {"article_id": 7218602, "funder": null}, {"article_id": 7218602, "funder": "Directorate for Biological Sciences"}, {"article_id": 7218602, "funder": "Directorate for Computer & Information Science & Engineering"}, {"article_id": 7464500, "funder": null}, {"article_id": 7125368, "funder": null}, {"article_id": 7017491, "funder": null}, {"article_id": 6531224, "funder": null}, {"article_id": 6851063, "funder": null}, {"article_id": 6850991, "funder": null}]